demtpy/__init__.py
demtpy/ahp.py
demtpy/topsis.py
dss/ahp.py
demtpy-0.1.1.dist-info/METADATA
demtpy-0.1.1.dist-info/WHEEL
demtpy-0.1.1.dist-info/top_level.txt
demtpy-0.1.1.dist-info/RECORD
