Metadata-Version: 2.4
Name: demtpy
Version: 0.1.1
Summary: Decision Support System implementation
Author-email: Milda Aditia Putra <aditia.putra100@gmail.com>
Requires-Python: >=3.9
Requires-Dist: numpy>=2.3.1
